jupyterlite_robotkernel/__init__.py
jupyterlite_robotkernel/_version.py
jupyterlite_robotkernel/addons/__init__.py
jupyterlite_robotkernel/addons/robotkernel.py
jupyterlite_robotkernel/addons/wheels.json
jupyterlite_robotkernel/labextension/package.json
jupyterlite_robotkernel/labextension/static/224.b76b27382bb96586c374.js
jupyterlite_robotkernel/labextension/static/349.5ef8ef8bbd44a18398ee.js
jupyterlite_robotkernel/labextension/static/375.86599eb43c193d1b1ff6.js
jupyterlite_robotkernel/labextension/static/496.13dfdf8fd42fbdb07421.js
jupyterlite_robotkernel/labextension/static/68278575914e7ddf8edfdb0588cd127d0e6728ad9ea7f0880a971269c96ea467.png
jupyterlite_robotkernel/labextension/static/747.ac5468aec0059b66c3d7.js
jupyterlite_robotkernel/labextension/static/remoteEntry.81dda4fff527ac1c0773.js
jupyterlite_robotkernel/labextension/static/style.js
jupyterlite_robotkernel/labextension/static/third-party-licenses.json
jupyterlite_robotkernel/labextension/static/pypi/all.json
jupyterlite_robotkernel/labextension/static/pypi/ipykernel-6.9.2-py3-none-any.whl
jupyterlite_robotkernel/labextension/static/pypi/piplite-0.1.0b4-py3-none-any.whl
jupyterlite_robotkernel/labextension/static/pypi/pyolite-0.1.0b4-py3-none-any.whl
jupyterlite_robotkernel/labextension/static/pypi/widgetsnbextension-3.6.0-py3-none-any.whl
jupyterlite_robotkernel-0.1.0a5.data/data/share/jupyter/labextensions/@jupyterlite/robolite-kernel-extension/install.json
jupyterlite_robotkernel-0.1.0a5.data/data/share/jupyter/labextensions/@jupyterlite/robolite-kernel-extension/package.json
jupyterlite_robotkernel-0.1.0a5.data/data/share/jupyter/labextensions/@jupyterlite/robolite-kernel-extension/static/224.b76b27382bb96586c374.js
jupyterlite_robotkernel-0.1.0a5.data/data/share/jupyter/labextensions/@jupyterlite/robolite-kernel-extension/static/349.5ef8ef8bbd44a18398ee.js
jupyterlite_robotkernel-0.1.0a5.dist-info/LICENSE
jupyterlite_robotkernel-0.1.0a5.dist-info/METADATA
jupyterlite_robotkernel-0.1.0a5.dist-info/WHEEL
jupyterlite_robotkernel-0.1.0a5.dist-info/entry_points.txt
jupyterlite_robotkernel-0.1.0a5.dist-info/top_level.txt
jupyterlite_robotkernel-0.1.0a5.dist-info/RECORD
