Metadata-Version: 2.1
Name: jupyterlite-robotkernel
Version: 0.1.0a5
Summary: A RobotFramework kernel for JupyterLite
Home-page: https://robotkernel.rtfd.io
Author: Asko Soukka
Author-email: asko.soukka@iki.fi
License: BSD-3-Clause
Project-URL: Bug Tracker, https://github.com/robots-from-jupyter/robotkernel/issues
Project-URL: Changelog, https://github.com/robots-from-jupyter/robotkernel/blob/master/CHANGELOG.rst
Project-URL: Documentation, https://robotkernel.rtfd.io
Project-URL: Source Code, https://github.com/robots-from-jupyter/robotkernel
Platform: UNKNOWN
Classifier: Development Status :: 4 - Beta
Classifier: Framework :: Jupyter
Classifier: Framework :: Jupyter :: JupyterLab :: 3
Classifier: Framework :: Jupyter :: JupyterLab :: Extensions
Classifier: Framework :: Jupyter :: JupyterLab :: Extensions :: Prebuilt
Classifier: Intended Audience :: Developers
Classifier: Intended Audience :: Information Technology
Classifier: License :: OSI Approved :: BSD License
Classifier: Programming Language :: Python
Classifier: Programming Language :: Python :: 3 :: Only
Classifier: Programming Language :: Python :: 3.6
Classifier: Programming Language :: Python :: 3.7
Classifier: Programming Language :: Python :: 3.8
Classifier: Programming Language :: Python :: 3.9
Classifier: Topic :: Multimedia :: Graphics :: Editors :: Vector-Based
Classifier: Topic :: Multimedia :: Graphics :: Presentation
Requires-Python: >=3.7
License-File: LICENSE
Requires-Dist: pkginfo
Requires-Dist: jupyterlab-widgets
Requires-Dist: jupyterlab-robotmode
Requires-Dist: jupyterlite (>=0.1.0b4)
